[
    { "name": "Tier 1", "pokemon": ["Accelgor","Alcremie","Amoonguss","Araquanid","Arcanine","Arctozolt","Bisharp","Blastoise","Bronzong","Carbink","Centiskorch","Chandelure","Charizard","Cinderace","Clefable","Clefairy","Coalossal","Cofagrigus","Comfey","Conkeldurr","Corviknight","Cradily","Darmanitan-Galar","Dracovish","Dracozolt","Dragapult","Dragonite","Drifblim","Duraludon","Durant","Dusclops","Escavalier","Excadrill","Ferrothorn","Garchomp","Gardevoir","Gastrodon","Gigalith","Goodra","Gothitelle","Grimmsnarl","Gyarados","Hatterene","Hawlucha","Hitmontop","Hydreigon","Incineroar","Indeedee","Indeedee-F","Inteleon","Kingdra","Krookodile","Lapras","Lycanroc","Mamoswine","Meowstic","Metagross","Mienshao","Milotic","Mimikyu","Mudsdale","Ninetales","Ninetales-Alola","Oranguru","Politoed","Porygon-Z","Porygon2","Primarina","Raichu","Raikou","Rhyperior","Rillaboom","Rotom-Heat","Rotom-Wash","Salamence","Sceptile","Scizor","Seismitoad","Shuckle","Slowbro","Slowbro-Galar","Slowking-Galar","Snorlax","Sylveon","Talonflame","Togekiss","Torkoal","Toxtricity","Tsareena","Turtonator","Tyranitar","Umbreon","Vanilluxe","Venusaur","Volcarona","Weavile","Weezing","Weezing-Galar","Whimsicott"]},
    { "name": "Tier 2", "pokemon": ["Abomasnow","Aegislash","Aggron","Alakazam","Appletun","Arctovish","Armaldo","Aromatisse","Aurorus","Avalugg","Barraskewda","Beartic","Bewear","Blaziken","Blissey","Bouffalant","Braviary","Clawitzer","Claydol","Crawdaunt","Crobat","Crustle","Cursola","Decidueye","Dhelmise","Dragalge","Drampa","Drapion","Drednaw","Dusknoir","Electivire","Espeon","Exeggutor","Exeggutor-Alola","Flareon","Froslass","Gallade","Gengar","Glaceon","Gourgeist-Super","Haxorus","Heliolisk","Hippowdon","Hitmonchan","Jellicent","Jolteon","Jynx","Kabutops","Kangaskhan","Klefki","Kommo-o","Lanturn","Leafeon","Lickilicky","Lilligant","Lopunny","Lucario","Ludicolo","Lurantis","Luxray","Machamp","Magnezone","Malamar","Mandibuzz","Manectric","Mantine","Mr. Mime","Mr. Mime-Galar","Nidoking","Nidoqueen","Noivern","Obstagoon","Octillery","Orbeetle","Palossand","Passimian","Poliwrath","Polteageist","Raichu-Alola","Reuniclus","Rhydon","Ribombee","Rotom-Frost","Rotom-Mow","Runerigus","Salazzle","Sandaconda","Scrafty","Sigilyph","Sirfetch'd","Slowking","Slurpuff","Spiritomb","Starmie","Steelix","Stonjourner","Stoutland","Swampert","Tangrowth","Tauros","Tentacruel","Thievul","Toxapex","Trevenant","Tyrantrum","Vaporeon","Vikavolt","Vileplume","Wishiwashi","Zoroark"]},
    { "name": "Tier 3", "pokemon": ["Absol","Aerodactyl","Altaria","Archeops","Barbaracle","Basculin","Beheeyem","Bellossom","Boltund","Carracosta","Cinccino","Cloyster","Copperajah","Cramorant","Cryogonal","Darmanitan","Druddigon","Dubwool","Eiscue","Eldegoss","Electabuzz","Exploud","Falinks","Flapple","Flygon","Frosmoth","Galvantula","Garbodor","Glalie","Golbat","Golduck","Golisopod","Golurk","Gourgeist","Gourgeist-Large","Gourgeist-Small","Grapploct","Greedent","Heatmor","Heracross","Hitmonlee","Kingler","Klinklang","Lunatone","Lycanroc-Dusk","Lycanroc-Midnight","Magmar","Magmortar","Magneton","Maractus","Miltank","Mr. Rime","Musharna","Ninjask","Noctowl","Omastar","Pangoro","Pinsir","Rapidash","Rapidash-Galar","Relicanth","Roserade","Rotom-Fan","Sawk","Scolipede","Scyther","Sharpedo","Shiftry","Skarmory","Skuntank","Sliggoo","Solrock","Stunfisk","Stunfisk-Galar","Throh","Toxicroak","Unfezant","Vespiquen","Wailord","Walrein","Whiscash","Xatu"]},
    { "name": "Banned", "pokemon": ["Abra","Amaura","Anorith","Applin","Archen","Aron","Arrokuda","Audino","Axew","Azumarill","Azurill","Bagon","Bergmite","Binacle","Blipbug","Boldore","Bonsly","Bounsweet","Brionne","Bronzor","Budew","Bulbasaur","Buneary","Bunnelby","Butterfree","Carkol","Carvanha","Caterpie","Chansey","Charjabug","Charmander","Charmeleon","Cherrim","Cherubi","Chinchou","Clauncher","Cleffa","Clobbopus","Combee","Combusken","Corphish","Corsola","Corsola-Galar","Corvisquire","Cottonee","Croagunk","Cubchoo","Cubone","Cufant","Cutiefly","Dartrix","Darumaka","Darumaka-Galar","Dedenne","Delibird","Dewpider","Diggersby","Diglett","Ditto","Dottler","Doublade","Dragonair","Drakloak","Dratini","Dreepy","Drifloon","Drilbur","Drizzile","Dugtrio","Dugtrio-Alola","Dunsparce","Duosion","Duskull","Eevee","Elekid","Elgyem","Emolga","Farfetch'd","Farfetch'd-Galar","Feebas","Ferroseed","Fletchinder","Fletchling","Fomantis","Foongus","Fraxure","Frillish","Gabite","Gastly","Gible","Gloom","Goldeen","Golett","Goomy","Gossifleur","Gothita","Gothorita","Grookey","Grovyle","Growlithe","Gurdurr","Hakamo-o","Happiny","Hatenna","Hattrem","Haunter","Helioptile","Herdier","Hippopotas","Honedge","Horsea","Igglybuff","Impidimp","Inkay","Ivysaur","Jigglypuff","Joltik","Kabuto","Kadabra","Kirlia","Klang","Koffing","Krabby","Krokorok","Kubfu","Lairon","Lampent","Lickitung","Liepard","Lileep","Lillipup","Linoone","Linoone-Galar","Litten","Litwick","Loudred","Luxio","Machoke","Machop","Magby","Magikarp","Magnemite","Mantyke","Mareanie","Marill","Marowak","Marowak-Alola","Marshtomp","Mawile","Meowth","Metang","Metapod","Mienfoo","Milcery","Mime Jr.","Morelull","Morgrem","Morpeko","Mudbray","Mudkip","Munchlax","Natu","Nickit","NidoranM","Nidorina","Nidorino","Nincada","Nuzleaf","Oddish","Omanyte","Onix","Palpitoad","Pancham","Pawniard","Pelipper","Perrserker","Persian","Persian-Alola","Phantump","Pichu","Pidove","Pikachu","Piloswine","Pincurchin","Poipole","Poliwag","Poliwhirl","Ponyta","Ponyta-Galar","Popplio","Porygon","Psyduck","Pumpkaboo-Super","Pupitar","Purrloin","Pyukumuku","Quagsire","Qwilfish","Raboot","Ralts","Remoraid","Rhyhorn","Riolu","Roggenrola","Rolycoly","Roselia","Rotom","Rowlet","Rufflet","Sableye","Salandit","Sandshrew","Sandslash","Sandslash-Alola","Sandygast","Scorbunny","Scraggy","Seadra","Seaking","Sealeo","Shedinja","Shelgon","Shellder","Shellos","Shiinotic","Shinx","Silicobra","Sinistea","Skorupi","Skrelp","Skwovet","Slowpoke","Slowpoke-Galar","Smoochum","Sneasel","Snom","Snorunt","Snover","Sobble","Solosis","Spheal","Spritzee","Squirtle","Staryu","Steenee","Stufful","Stunky","Sudowoodo","Swinub","Swirlix","Swoobat","Tangela","Thwackey","Tirtouga","Togedemaru","Togepi","Togetic","Torracat","Toxel","Tranquill","Trapinch","Treecko","Trubbish","Tympole","Tyrogue","Tyrunt","Vanillish","Vanillite","Vullaby","Vulpix","Vulpix-Alola","Wailmer","Wartortle","Whirlipede","Wigglytuff","Wimpod","Wingull","Wobbuffet","Woobat","Wooloo","Wooper","Wynaut","Yamask","Yamask-Galar","Yamper","Zigzagoon","Zigzagoon-Galar","Zorua","Zubat","Zweilous"] }
]